<?xml version="1.0" encoding="UTF-8"?>
<objects serializationModel="Studio.02.00.00">
	<object class="ParameterPreset" id="{d37895eb-07bb-4084-815e-8149f0ec1f05}">
		<property name="name">
			<value>Dialogue Volume</value>
		</property>
		<relationship name="folder">
			<destination>{29f8ba2b-6b4c-445c-98d6-95934370987e}</destination>
		</relationship>
		<relationship name="parameter">
			<destination>{79d6d920-673c-4533-9d86-5d384338e2e4}</destination>
		</relationship>
	</object>
	<object class="GameParameter" id="{79d6d920-673c-4533-9d86-5d384338e2e4}">
		<property name="maximum">
			<value>110</value>
		</property>
		<property name="isGlobal">
			<value>true</value>
		</property>
		<property name="initialValue">
			<value>100</value>
		</property>
		<property name="isExposedRecursively">
			<value>false</value>
		</property>
	</object>
</objects>
